tsassure_feature/__init__.py
tsassure_feature/feature_extractor.py
tsassure_feature/main.py
tsassure_feature-0.7.dist-info/METADATA
tsassure_feature-0.7.dist-info/WHEEL
tsassure_feature-0.7.dist-info/entry_points.txt
tsassure_feature-0.7.dist-info/top_level.txt
tsassure_feature-0.7.dist-info/RECORD
