Metadata-Version: 2.1
Name: tsassure-feature
Version: 0.7
Summary: UNKNOWN
License: UNKNOWN
Keywords: feature time-series feature_extraction
Platform: UNKNOWN
Requires-Dist: numpy
Requires-Dist: pandas
Requires-Dist: openpyxl
